[[0.304384,{"lines":{"0":[["skuater@pekeniajo:/media/skuater/Trabajo/RETOS/picoctf/baleful/doc/plugingR2$ r2 -w vm.code                                                                                                                  ",{}]],"1":[[" -- Remember to maintain your ~/.radar                                                                                                                                                                       ",{}]],"2":[["                                                                                                                                                                                                             ",{}]],"3":[["                                                                                                                                                                                                             ",{}]],"4":[["                                                                                                                                                                                                             ",{}]],"5":[["                                                                                                                                                                                                             ",{}]],"6":[["                                                                                                                                                                                                             ",{}]],"7":[["                                                                                                                                                                                                             ",{}]],"8":[["                                                                                                                                                                                                             ",{}]],"9":[["                                                                                                                                                                                                             ",{}]],"10":[["                                                                                                                                                                                                             ",{}]],"11":[["                                                                                                                                                                                                             ",{}]],"12":[["                                                                                                                                                                                                             ",{}]],"13":[["                                                                                                                                                                                                             ",{}]],"14":[["                                                                                                                                                                                                             ",{}]],"15":[["                                                                                                                                                                                                             ",{}]],"16":[["                                                                                                                                                                                                             ",{}]],"17":[["                                                                                                                                                                                                             ",{}]],"18":[["                                                                                                                                                                                                             ",{}]],"19":[["                                                                                                                                                                                                             ",{}]],"20":[["                                                                                                                                                                                                             ",{}]],"21":[["                                                                                                                                                                                                             ",{}]],"22":[["                                                                                                                                                                                                             ",{}]],"23":[["                                                                                                                                                                                                             ",{}]],"24":[["                                                                                                                                                                                                             ",{}]],"25":[["                                                                                                                                                                                                             ",{}]],"26":[["                                                                                                                                                                                                             ",{}]],"27":[["                                                                                                                                                                                                             ",{}]],"28":[["                                                                                                                                                                                                             ",{}]],"29":[["                                                                                                                                                                                                             ",{}]],"30":[["                                                                                                                                                                                                             ",{}]],"31":[["                                                                                                                                                                                                             ",{}]],"32":[["                                                                                                                                                                                                             ",{}]],"33":[["                                                                                                                                                                                                             ",{}]],"34":[["                                                                                                                                                                                                             ",{}]],"35":[["                                                                                                                                                                                                             ",{}]],"36":[["                                                                                                                                                                                                             ",{}]],"37":[["                                                                                                                                                                                                             ",{}]],"38":[["                                                                                                                                                                                                             ",{}]],"39":[["                                                                                                                                                                                                             ",{}]],"40":[["                                                                                                                                                                                                             ",{}]],"41":[["                                                                                                                                                                                                             ",{}]],"42":[["                                                                                                                                                                                                             ",{}]],"43":[["                                                                                                                                                                                                             ",{}]],"44":[["                                                                                                                                                                                                             ",{}]],"45":[["                                                                                                                                                                                                             ",{}]],"46":[["                                                                                                                                                                                                             ",{}]],"47":[["                                                                                                                                                                                                             ",{}]],"48":[["                                                                                                                                                                                                             ",{}]],"49":[["                                                                                                                                                                                                             ",{}]],"50":[["                                                                                                                                                                                                             ",{}]],"51":[["                                                                                                                                                                                                             ",{}]],"52":[["                                                                                                                                                                                                             ",{}]],"53":[["                                                                                                                                                                                                             ",{}]],"54":[["                                                                                                                                                                                                             ",{}]],"55":[["                                                                                                                                                                                                             ",{}]]},"cursor":{"x":38,"y":1,"visible":true}}],[0.000515,{"lines":{"1":[[" -- Remember to maintain your ~/.radare_history                                                                                                                                                              ",{}]]},"cursor":{"x":0,"y":2}}],[8.063252,{"lines":{"2":[["[0x00",{"fg":3}],["                                                                                                                                                                                                        ",{}]]},"cursor":{"x":5}}],[0.641846,{"lines":{"2":[["[0x00000000]>",{"fg":3}],[" s 0x10                                                                                                                                                                                         ",{}]]},"cursor":{"x":0}}],[0.204018,{"cursor":{"x":6}}],[0.252477,{"cursor":{"x":13}}],[0.105854,{"cursor":{"x":20}}],[0.257998,{"lines":{"2":[["                                                                                                                                                                                                             ",{}]]},"cursor":{"x":0}}],[0.934108,{"lines":{"2":[["[0x00",{"fg":3}],["                                                                                                                                                                                                        ",{}]]},"cursor":{"x":5}}],[0.324666,{"lines":{"2":[["[0x00000000]>",{"fg":3}],["                                                                                                                                                                                                ",{}]]},"cursor":{"x":13}}],[2.6e-05,{"lines":{"2":[["[0x00000000]>",{"fg":3}],[" s 0x1035                                                                                                                                                                                       ",{}]],"3":[["[0x000",{"fg":3}],["                                                                                                                                                                                                       ",{}]]},"cursor":{"x":6,"y":3}}],[0.739609,{"lines":{"3":[["[0x00001035]>",{"fg":3}],["                                                                                                                                                                                                ",{}]]},"cursor":{"x":13}}],[0.149572,{"cursor":{"x":0}}],[0.196462,{"cursor":{"x":13}}],[0.360658,{"lines":{"3":[["[0x00001035]>",{"fg":3}],[" e                                                                                                                                                                                              ",{}]]}}],[0.309478,{"cursor":{"x":16}}],[0.003372,{"lines":{"3":[["[0x00001035]>",{"fg":3}],[" e asm.arc                                                                                                                                                                                      ",{}]]},"cursor":{"x":17}}],[1.089821,{"lines":{"3":[["[0x00001035]>",{"fg":3}],[" e asm.arch                                                                                                                                                                                     ",{}]]},"cursor":{"x":23}}],[0.175435,{"lines":{"3":[["[0x00001035]>",{"fg":3}],[" e asm.arch=                                                                                                                                                                                    ",{}]]},"cursor":{"x":24}}],[1.139434,{"lines":{"3":[["[0x0000",{"fg":3}],["                                                                                                                                                                                                      ",{}]]},"cursor":{"x":7}}],[0.358366,{"lines":{"3":[["[0x00001",{"fg":3}],["                                                                                                                                                                                                     ",{}]]},"cursor":{"x":8}}],[0.234432,{"lines":{"3":[["[0x00",{"fg":3}],["                                                                                                                                                                                                        ",{}]]},"cursor":{"x":5}}],[0.394403,{"lines":{"3":[["[0x00001035]>",{"fg":3}],[" e asm.arch=b                                                                                                                                                                                   ",{}]]},"cursor":{"x":26}}],[1.098494,{"lines":{"3":[["[0x00001035]>",{"fg":3}],[" e asm.a                                                                                                                                                                                        ",{}]]},"cursor":{"x":21}}],[0.33074,{"lines":{"3":[["[0x00001035]>",{"fg":3}],[" e asm.arch=bale                                                                                                                                                                                ",{}]]},"cursor":{"x":11}}],[0.507037,{"lines":{"3":[["[0",{"fg":3}],["                                                                                                                                                                                                           ",{}]]},"cursor":{"x":2}}],[0.001344,{"lines":{"3":[["[0x00001035]>",{"fg":3}],[" e asm.arch=baleful                                                                                                                                                                             ",{}]],"4":[["[0x00001035]>",{"fg":3}],[" e as                                                                                                                                                                                           ",{}]]},"cursor":{"x":13,"y":4}}],[1.63638,{"cursor":{"x":16}}]]